jarm.py
setup.py
jarm.egg-info/PKG-INFO
jarm.egg-info/SOURCES.txt
jarm.egg-info/dependency_links.txt
jarm.egg-info/top_level.txt