Metadata-Version: 1.1
Name: jarm
Version: 0.1.0
Summary: The smarter, faster pip.
Home-page: UNKNOWN
Author: rayan haddad
Author-email: rayan.m.haddad@proton.me
License: MIT
Platform: any
Classifier: Development Status :: 4 - Beta
Classifier: Operating System :: OS Independent
Classifier: Intended Audience :: Developers
Classifier: License :: OSI Approved :: MIT License
Classifier: Programming Language :: Python :: 2.7
Classifier: Programming Language :: Python :: 3
Classifier: Programming Language :: Python :: 3.6
Classifier: Programming Language :: Python :: 3.7
Classifier: Programming Language :: Python :: 3.8
Classifier: Programming Language :: Python :: 3.9
